    [
        {
            "id": "clement.depres",
            "displayName": "Clément Depres",
            "avatar": "/avatars/0.png"
        },
        {
            "id": "kilian.corredor",
            "displayName": "Kilian Corredor",
            "avatar": "/avatars/1.png"
        },
        {
            "id": "erwan.maintenant",
            "displayName": "Erwan Maintenant",
            "avatar": "/avatars/2.png"
        },
        {
            "id": "leo.queguiner",
            "displayName": "Leo Queguiner",
            "avatar": "/avatars/3.png"
        },
        {
            "id": "ronan.le.coupanec",
            "displayName": "Ronan Le Coupanec",
            "avatar": "/avatars/4.png"
        },
        {
            "id": "christophe.jallet",
            "displayName": "Christophe Jallet",
            "avatar": "/avatars/5.png"
        },
        {
            "id": "talal.el.karkouri",
            "displayName": "Talal El Karkouri",
            "avatar": "/avatars/6.png"
        },
        {
            "id": "ali.benarbia",
            "displayName": "Ali Benarbia",
            "avatar": "/avatars/7.png"
        },
        {
            "id": "lionel.letizi",
            "displayName": "Lionel Letizi",
            "avatar": "/avatars/8.png"
        }
    ]